luda/__init__.py
luda/cli.py
luda/config.py
luda/luda.py
luda/utils.py
luda/bootstrap/init.sh
luda/bootstrap/su-exec
luda-0.4.4.dist-info/DESCRIPTION.rst
luda-0.4.4.dist-info/METADATA
luda-0.4.4.dist-info/RECORD
luda-0.4.4.dist-info/WHEEL
luda-0.4.4.dist-info/entry_points.txt
luda-0.4.4.dist-info/metadata.json
luda-0.4.4.dist-info/top_level.txt
