Metadata-Version: 2.0
Name: luda
Version: 0.4.4
Summary: ludicrously awesome [w]rapper for nvidia-docker
Home-page: https://github.com/ryanolson/luda
Author: Ryan Olson
Author-email: rmolson@gmail.com
License: MIT license
Keywords: luda
Platform: UNKNOWN
Classifier: Development Status :: 2 - Pre-Alpha
Classifier: Intended Audience :: Developers
Classifier: License :: OSI Approved :: MIT License
Classifier: Natural Language :: English
Classifier: Programming Language :: Python :: 2
Classifier: Programming Language :: Python :: 2.7
Requires-Dist: Click (>=6.0)
Requires-Dist: docker (>=2.3.0)
Requires-Dist: j2docker (>=0.1.0)
Requires-Dist: jinja2 (>=2.9.6)
Requires-Dist: poyo (>=0.4.1)
